xchk_core/__init__.py
xchk_core/admin.py
xchk_core/apps.py
xchk_core/consumers.py
xchk_core/contentviews.py
xchk_core/context_processors.py
xchk_core/courses.py
xchk_core/forms.py
xchk_core/migrations/0001_initial.py
xchk_core/migrations/0002_auto_20200814_1612.py
xchk_core/migrations/0003_auto_20200820_1105.py
xchk_core/migrations/0004_auto_20200820_1213.py
xchk_core/migrations/__init__.py
xchk_core/models.py
xchk_core/routing.py
xchk_core/setup.py
xchk_core/signals/handlers.py
xchk_core/static/xchk_core/LICENSE.txt
xchk_core/static/xchk_core/css/all.css
xchk_core/static/xchk_core/css/all.min.css
xchk_core/static/xchk_core/css/brands.css
xchk_core/static/xchk_core/css/brands.min.css
xchk_core/static/xchk_core/css/fontawesome.css
xchk_core/static/xchk_core/css/fontawesome.min.css
xchk_core/static/xchk_core/css/regular.css
xchk_core/static/xchk_core/css/regular.min.css
xchk_core/static/xchk_core/css/solid.css
xchk_core/static/xchk_core/css/solid.min.css
xchk_core/static/xchk_core/css/svg-with-js.css
xchk_core/static/xchk_core/css/svg-with-js.min.css
xchk_core/static/xchk_core/css/v4-shims.css
xchk_core/static/xchk_core/css/v4-shims.min.css
xchk_core/static/xchk_core/js/all.js
xchk_core/static/xchk_core/js/all.min.js
xchk_core/static/xchk_core/js/brands.js
xchk_core/static/xchk_core/js/brands.min.js
xchk_core/static/xchk_core/js/conflict-detection.js
xchk_core/static/xchk_core/js/conflict-detection.min.js
xchk_core/static/xchk_core/js/fontawesome.js
xchk_core/static/xchk_core/js/fontawesome.min.js
xchk_core/static/xchk_core/js/regular.js
xchk_core/static/xchk_core/js/regular.min.js
xchk_core/static/xchk_core/js/solid.js
xchk_core/static/xchk_core/js/solid.min.js
xchk_core/static/xchk_core/js/springy.js
xchk_core/static/xchk_core/js/springyui.js
xchk_core/static/xchk_core/js/v4-shims.js
xchk_core/static/xchk_core/js/v4-shims.min.js
xchk_core/static/xchk_core/less/_animated.less
xchk_core/static/xchk_core/less/_bordered-pulled.less
xchk_core-0.2.8.dist-info/WHEEL
xchk_core-0.2.8.dist-info/METADATA
xchk_core-0.2.8.dist-info/RECORD
